README
setup.py
timus/__init__.py
timus.scoreboard.egg-info/PKG-INFO
timus.scoreboard.egg-info/SOURCES.txt
timus.scoreboard.egg-info/dependency_links.txt
timus.scoreboard.egg-info/entry_points.txt
timus.scoreboard.egg-info/requires.txt
timus.scoreboard.egg-info/top_level.txt
timus/scoreboard/__init__.py
timus/scoreboard/tests.py