Metadata-Version: 1.0
Name: timus.scoreboard
Version: 0.2
Summary: Custom contest support for the Timus Online Judge
Home-page: http://github.com/admp/timus-scoreboard
Author: Adomas Paltanavicius
Author-email: adomas@shrubberysoft.com
License: UNKNOWN
Platform: UNKNOWN
Classifier: Development Status :: 4 - Beta
Classifier: Environment :: Console
Classifier: License :: OSI Approved :: MIT License
Classifier: Topic :: Education
